{
  "date": "2026-07-15",
  "day_name": "Wednesday",
  "warm_up": "10 minute timer\nWarm Up Equipment:\nBlack/Green Band\nEmpty Bar\n40% DL Bar\n2 Rounds:\n30 sec Hollow Hold\n15sec e/s Side Plank\nBanded Row\n15 BB Good Morning\n15 BB RDL\n8 Hip Thrust @ 40% DL",
  "strength": [
    {
      "name": "Deadlift",
      "description": "4x6 | Double Pause Deadlift\n* Pause just off floor & at knee\n* Wedge Hips into the bar\n* Shoulder Blades to back pocket | 12mins\nE3MOMx4\n0:00 6 @ 45%\n3:00 6 @ 45%\n6:00 6 @ 45%\n9:00 6 @ 45%"
    },
    {
      "name": "Romanian Deadlift (RDL)",
      "description": "4x8 | 12mins\nE3MOMx4\n0:00 8 @ 45%\n3:00 8 @ 45%\n6:00 8 @ 45%\n9:00 8 @ 45%"
    },
    {
      "name": "Seated Cable Row",
      "description": "3x10"
    },
    {
      "name": "Hamstring Curl",
      "description": "3x10"
    }
  ],
  "metcon": {
    "name": "Workout",
    "type": "AMRAP",
    "description": "15 min AMRAP\n400m Run\n6 Deadlift 100/70\n8 T2B",
    "time_cap": null
  },
  "gymnastics": [],
  "hypertrophy": {
    "recommended_muscles": [
      "chest",
      "shoulders",
      "biceps"
    ],
    "avoid": [
      "hamstrings",
      "lower back",
      "glutes",
      "core"
    ],
    "reasoning": "Today emphasizes posterior chain and core; anterior upper body remains fresh for hypertrophy without competing for recovery.",
    "suggested_exercises": [
      "Dumbbell Bench Press: 3x8",
      "Incline Dumbbell Flyes: 3x10",
      "Lateral Raises: 3x12",
      "Barbell Curls: 3x8"
    ]
  },
  "raw_text": "Warm Up | 10 minute timer\nWarm Up Equipment:\nBlack/Green Band\nEmpty Bar\n40% DL Bar\n2 Rounds:\n30 sec Hollow Hold\n15sec e/s Side Plank\nBanded Row\n15 BB Good Morning\n15 BB RDL\n8 Hip Thrust @ 40% DL\nDeadlift | 4x6 | Double Pause Deadlift\n* Pause just off floor & at knee\n* Wedge Hips into the bar\n* Shoulder Blades to back pocket | 12mins\nE3MOMx4\n0:00 6 @ 45%\n3:00 6 @ 45%\n6:00 6 @ 45%\n9:00 6 @ 45%\nRomanian Deadlift (RDL) | 4x8 | 12mins\nE3MOMx4\n0:00 8 @ 45%\n3:00 8 @ 45%\n6:00 8 @ 45%\n9:00 8 @ 45%\nWorkout | 15 min AMRAP\n400m Run\n6 Deadlift 100/70\n8 T2B\nSeated Cable Row | 3x10\nHamstring Curl | 3x10",
  "siri_text": "Wednesday's workout. Strength: Deadlift, 4 by 6 at 45 percent. Strength: Romanian Deadlift (RDL), 4 by 8 at 45 percent. Strength: Seated Cable Row, 3 by 10. Strength: Hamstring Curl, 3 by 10. Metcon: AMRAP 15 minutes: 400m Run, 6 Deadlift 100/70, 8 T2B. For hypertrophy, focus on chest, shoulders, biceps."
}